.gitignore
CHANGES.txt
MANIFEST.in
README.md
setup.py
djinn_contenttypes/__init__.py
djinn_contenttypes/__init__.pyc
djinn_contenttypes/registry.py
djinn_contenttypes/registry.pyc
djinn_contenttypes/settings.py
djinn_contenttypes/settings.pyc
djinn_contenttypes/urls.py
djinn_contenttypes/urls.pyc
djinn_contenttypes/utils.py
djinn_contenttypes/utils.pyc
djinn_contenttypes.egg-info/PKG-INFO
djinn_contenttypes.egg-info/SOURCES.txt
djinn_contenttypes.egg-info/dependency_links.txt
djinn_contenttypes.egg-info/entry_points.txt
djinn_contenttypes.egg-info/not-zip-safe
djinn_contenttypes.egg-info/requires.txt
djinn_contenttypes.egg-info/top_level.txt
djinn_contenttypes/.idea/djinn_contenttypes.iml
djinn_contenttypes/.idea/encodings.xml
djinn_contenttypes/.idea/misc.xml
djinn_contenttypes/.idea/modules.xml
djinn_contenttypes/.idea/vcs.xml
djinn_contenttypes/.idea/workspace.xml
djinn_contenttypes/.idea/scopes/scope_settings.xml
djinn_contenttypes/forms/__init__.py
djinn_contenttypes/forms/__init__.pyc
djinn_contenttypes/forms/base.py
djinn_contenttypes/forms/base.pyc
djinn_contenttypes/forms/fields.py
djinn_contenttypes/forms/fields.pyc
djinn_contenttypes/forms/imgattachment.py
djinn_contenttypes/forms/imgattachment.pyc
djinn_contenttypes/forms/share.py
djinn_contenttypes/forms/share.pyc
djinn_contenttypes/locale/en_EN/LC_MESSAGES/django.mo
djinn_contenttypes/locale/en_EN/LC_MESSAGES/django.po
djinn_contenttypes/locale/nl_NL/LC_MESSAGES/django.mo
djinn_contenttypes/locale/nl_NL/LC_MESSAGES/django.po
djinn_contenttypes/management/__init__.py
djinn_contenttypes/management/__init__.pyc
djinn_contenttypes/management/commands/__init__.py
djinn_contenttypes/management/commands/__init__.pyc
djinn_contenttypes/management/commands/publish.py
djinn_contenttypes/management/commands/publish.pyc
djinn_contenttypes/management/commands/unpublish.py
djinn_contenttypes/management/commands/unpublish.pyc
djinn_contenttypes/models/__init__.py
djinn_contenttypes/models/__init__.pyc
djinn_contenttypes/models/attachment.py
djinn_contenttypes/models/attachment.pyc
djinn_contenttypes/models/base.py
djinn_contenttypes/models/base.pyc
djinn_contenttypes/models/commentable.py
djinn_contenttypes/models/commentable.pyc
djinn_contenttypes/models/highlight.py
