Metadata-Version: 1.1
Name: djinn-contenttypes
Version: 1.4.8
Summary: Djinn Intranet Contenttypes framework
Home-page: https://github.com/PythonUnited/djinn-contenttypes
Author: PythonUnited
Author-email: info@pythonunited.com
License: beer-ware
Keywords: Djinn Contenttypes
Platform: UNKNOWN
Classifier: Development Status :: 5 - Production/Stable
Classifier: Framework :: Django
Classifier: Intended Audience :: Developers
Classifier: License :: Freely Distributable
Classifier: Programming Language :: Python
Classifier: Topic :: Internet :: WWW/HTTP :: Site Management
Classifier: Topic :: Software Development :: Libraries :: Application Frameworks
